[
  {
    "id": "https://news.walla.co.il/item/3828225",
    "title": "מנהיג בורקינה פאסו: \"שכחו מדמוקרטיה, היא הורגת\"",
    "description": "מנהיג בורקינה פאסו: \"שכחו מדמוקרטיה, היא הורגת\"  וואלה חדשות",
    "url": "https://news.walla.co.il/item/3828225",
    "image": "https://images.wcdn.co.il/f_auto,q_auto,w_1200,t_54/4/0/3/4/4034123-46.jpg",
    "timestamp": 1775222820000,
    "source": "וואלה חדשות",
    "publisher_id": "news.walla.co.il",
    "type": "article",
    "google_url": "https://news.google.com/rss/articles/CBMiTkFVX3lxTE5PRU5EYWhlak94ZnNPSWVxRXFTTUNfMkNrNG9ZUkdiUkRNaTkwekFNLVIzNm1uT1FzSVZ6dGZIZU1MQ2kwMXRpaUVQN25ZZw?oc=5",
    "rssid": "laN220",
    "topic": "news",
    "lang": "general",
    "category": "العبرية",
    "extra": "Burkina Faso",
    "likes": 0,
    "comments": 0
  }
]