[
  {
    "id": "https://www.maariv.co.il/news/world/article-1320190",
    "title": "הדיווח שמסבך את פקיסטן: הסתירה מטוסים איראניים מפני הצבא האמריקאי",
    "description": "הדיווח שמסבך את פקיסטן: הסתירה מטוסים איראניים מפני הצבא האמריקאי  מעריב",
    "url": "https://www.maariv.co.il/news/world/article-1320190",
    "image": "https://images.maariv.co.il/image/upload/f_auto,fl_lossy/c_fill,g_faces:center,w_1200/1087258",
    "timestamp": 1778529180000,
    "source": "מעריב",
    "publisher_id": "www.maariv.co.il",
    "type": "article",
    "google_url": "https://news.google.com/rss/articles/CBMiYEFVX3lxTE9VaEVXTW5aMlBzYVVBdW1fNk9EcDkzS1NJdHNQWkFUazgtNTBtMUlBZEdpZkd6SUlFQWZ2elZGa3BXTThublVwSmFZcVNvek5wQ0g3eDdrazJiSG9xQThhQw?oc=5",
    "rssid": "laN323",
    "topic": "news",
    "lang": "general",
    "category": "العبرية",
    "extra": "Pakistan",
    "likes": 0,
    "comments": 0
  }
]