[
  {
    "id": "https://m.technologijos.lt/cat/26068/article/S-232417",
    "title": "Pamirškite F-35: į dangų kyla pigesnis „monstras“, kuriam prognozuojama neįtikėtina sėkmė (Video)",
    "description": "Pamirškite F-35: į dangų kyla pigesnis „monstras“, kuriam prognozuojama neįtikėtina sėkmė (Video)  Technologijos",
    "url": "https://m.technologijos.lt/cat/26068/article/S-232417",
    "image": "https://m.technologijos.lt/photo/202603/27/06/800_540078__1.jpg",
    "timestamp": 1774760443000,
    "source": "Technologijos",
    "publisher_id": "m.technologijos.lt",
    "type": "article",
    "google_url": "https://news.google.com/rss/articles/CBMiY0FVX3lxTE1XUzNtQlJMbDhyTzhieVVocTRVX2xtX1hZcWx0OEV1OXI3bzctb3drOTRYY0FqTDA5N3hBVzlVeFlhQmUyTVFrYzd0aTlGSHpCR0ROZnJCNjRlRTg1ZU81V2VkNA?oc=5",
    "rssid": "laN522",
    "topic": "news",
    "lang": "general",
    "category": "الليتوانية",
    "extra": "Philippines",
    "likes": 0,
    "comments": 0
  }
]